Metadata-Version: 2.1
Name: django-correos-chile
Version: 1.2.2
Summary: Django Correos Chile Integration
Home-page: https://gitlab.com/linets/ecommerce/oms/integrations/oms-correos-chile/
Author: Linets Development Team
Author-email: dteam@linets.cl
License: MIT
Platform: UNKNOWN
Requires-Python: >=3.7
